templateproj/__init__.py
templateproj/templateproj.py
templateproj-1.0.1.dist-info/LICENSE
templateproj-1.0.1.dist-info/METADATA
templateproj-1.0.1.dist-info/WHEEL
templateproj-1.0.1.dist-info/top_level.txt
templateproj-1.0.1.dist-info/RECORD
