Metadata-Version: 2.1
Name: templateproj
Version: 1.0.1
Summary: Write Your Package Description Here
Home-page: https://github.com/bdfd
Author: BDFD
Author-email: bdfd2005@gmail.com
License: UNKNOWN
Project-URL: Bug Tracker, https://github.com/bdfd
Platform: UNKNOWN
Classifier: Programming Language :: Python :: 3
Classifier: License :: OSI Approved :: MIT License
Classifier: Operating System :: OS Independent
Requires-Python: >=3.6
License-File: LICENSE
